mmelemental/__init__.py
mmelemental/_version.py
mmelemental/extras.py
mmelemental/mmelemental.py
mmelemental/data/README.md
mmelemental/data/look_and_say.dat
mmelemental/data/imgs/mmelemental.png
mmelemental/models/__init__.py
mmelemental/models/base.py
mmelemental/models/collect/__init__.py
mmelemental/models/collect/trajectory.py
mmelemental/models/forcefield/__init__.py
mmelemental/models/forcefield/forcefield.py
mmelemental/models/forcefield/params.py
mmelemental/models/forcefield/bonded/__init__.py
mmelemental/models/forcefield/bonded/angles/__init__.py
mmelemental/models/forcefield/bonded/angles/base.py
mmelemental/models/forcefield/bonded/angles/potentials/__init__.py
mmelemental/models/forcefield/bonded/angles/potentials/harmonic.py
mmelemental/models/forcefield/bonded/bonds/__init__.py
mmelemental/models/forcefield/bonded/bonds/base.py
mmelemental/models/forcefield/bonded/bonds/potentials/__init__.py
mmelemental/models/forcefield/bonded/bonds/potentials/gromos96.py
mmelemental/models/forcefield/bonded/bonds/potentials/harmonic.py
mmelemental/models/forcefield/bonded/dihedrals/__init__.py
mmelemental/models/forcefield/bonded/dihedrals/base.py
mmelemental/models/forcefield/bonded/dihedrals/potentials/__init__.py
mmelemental/models/forcefield/bonded/dihedrals/potentials/charmm.py
mmelemental/models/forcefield/bonded/dihedrals/potentials/charmm_multi.py
mmelemental/models/forcefield/bonded/dihedrals/potentials/harmonic.py
mmelemental/models/forcefield/bonded/dihedrals_improper/__init__.py
mmelemental/models/forcefield/bonded/dihedrals_improper/base.py
mmelemental/models/forcefield/bonded/dihedrals_improper/potentials/__init__.py
mmelemental/models/forcefield/bonded/dihedrals_improper/potentials/charmm.py
mmelemental/models/forcefield/bonded/dihedrals_improper/potentials/charmm_multi.py
mmelemental/models/forcefield/bonded/dihedrals_improper/potentials/harmonic.py
mmelemental/models/forcefield/nonbonded/__init__.py
mmelemental-0.1.1.dist-info/LICENSE
mmelemental-0.1.1.dist-info/METADATA
mmelemental-0.1.1.dist-info/WHEEL
mmelemental-0.1.1.dist-info/top_level.txt
mmelemental-0.1.1.dist-info/zip-safe
mmelemental-0.1.1.dist-info/RECORD
