Metadata-Version: 2.1
Name: mmelemental
Version: 0.1.1
Summary: UNKNOWN
Home-page: UNKNOWN
Author: MolSSI
Author-email: support@molssi.edu
License: BSD-3-Clause
Platform: UNKNOWN
Classifier: Development Status :: 3 - Alpha
Classifier: Intended Audience :: Science/Research
Classifier: Programming Language :: Python :: 3 :: Only
Classifier: Programming Language :: Python :: 3.9
Classifier: Programming Language :: Python :: 3.10
Requires-Python: >=3.9
Requires-Dist: pint
Requires-Dist: cmselemental
